rmtoo/__init__.py
rmtoo/contrib/favicon-16x16.png
rmtoo/contrib/favicon-32x32.png
rmtoo/contrib/gnuplot_stats_burndown.inc
rmtoo/contrib/gnuplot_stats_reqs_cnt.inc
rmtoo/contrib/gnuplot_stats_sprint_burndown.inc
rmtoo/contrib/license-header.txt
rmtoo/contrib/req-mode.el
rmtoo/contrib/rmtoo_icon.png
rmtoo/contrib/rmtoo_icon.xcf
rmtoo/contrib/xml2ganttproject.xsl
rmtoo/gui1/__init__.py
rmtoo/gui1/view_only.py
rmtoo/gui1/view_only2.py
rmtoo/imports/__init__.py
rmtoo/imports/abcimports.py
rmtoo/imports/xls.py
rmtoo/inputs/RDepConstraints.py
rmtoo/inputs/RDepDependsOn.py
rmtoo/inputs/RDepMasterNodes.py
rmtoo/inputs/RDepNoDirectedCircles.py
rmtoo/inputs/RDepOneComponent.py
rmtoo/inputs/RDepPriority.py
rmtoo/inputs/RDepSolvedBy.py
rmtoo/inputs/ReqCE3.py
rmtoo/inputs/ReqClass.py
rmtoo/inputs/ReqConstraints.py
rmtoo/inputs/ReqDescription.py
rmtoo/inputs/ReqEffortEst.py
rmtoo/inputs/ReqExpectedResult.py
rmtoo/inputs/ReqHistory.py
rmtoo/inputs/ReqInventedBy.py
rmtoo/inputs/ReqInventedOn.py
rmtoo/inputs/ReqName.py
rmtoo/inputs/ReqNote.py
rmtoo/inputs/ReqOwner.py
rmtoo/inputs/ReqPriority.py
rmtoo/inputs/ReqRationale.py
rmtoo/inputs/ReqStatus.py
rmtoo/inputs/ReqTestCase.py
rmtoo/inputs/ReqTopic.py
rmtoo/inputs/ReqType.py
rmtoo/inputs/__init__.py
rmtoo/lib/Analytics.py
rmtoo/lib/BaseRMObject.py
rmtoo/lib/CE3.py
rmtoo/lib/CE3Set.py
rmtoo/lib/ClassType.py
rmtoo/lib/Constraint.py
rmtoo/lib/Constraints.py
rmtoo/lib/CreateMakeDependencies.py
rmtoo/lib/DateUtils.py
rmtoo/lib/Encoding.py
rmtoo/lib/Executor.py
rmtoo/lib/ExecutorTopicContinuum.py
rmtoo/lib/FuncCall.py
rmtoo/lib/GenIterator.py
rmtoo/lib/Import.py
rmtoo/lib/InputModuleTypes.py
rmtoo/lib/InputModules.py
rmtoo/lib/Markup.py
rmtoo/lib/Output.py
rmtoo/lib/RMTException.py
rmtoo/lib/ReqTagGeneric.py
rmtoo/lib/Requirement.py
rmtoo/lib/RequirementSet.py
rmtoo/lib/RequirementStatus.py
rmtoo/lib/RmtooMain.py
rmtoo/lib/Statistics.py
rmtoo/lib/StdOutputParams.py
rmtoo/lib/StringHelper.py
rmtoo/lib/TestCase.py
rmtoo/lib/TestCases.py
sltoo-25.0.5.dist-info/entry_points.txt
sltoo-25.0.5.dist-info/COPYING
sltoo-25.0.5.dist-info/LICENSE
sltoo-25.0.5.dist-info/WHEEL
sltoo-25.0.5.dist-info/METADATA
sltoo-25.0.5.dist-info/RECORD
