Metadata-Version: 2.1
Name: sltoo
Version: 25.0.5
Summary: rmtoo
Home-page: https://github.com/kown7/rmtoo
Author: Kristoffer Nordström
Author-email: kristoffer@nordstroem.ch
Classifier: Development Status :: 6 - Mature
Classifier: Environment :: Console
Classifier: Intended Audience :: Developers
Classifier: Intended Audience :: Education
Classifier: Intended Audience :: End Users/Desktop
Classifier: Intended Audience :: Manufacturing
Classifier: Intended Audience :: Telecommunications Industry
Classifier: License :: OSI Approved :: GNU General Public License v3 or later (GPLv3+)
Classifier: Operating System :: MacOS
Classifier: Operating System :: Microsoft :: Windows
Classifier: Operating System :: OS Independent
Classifier: Operating System :: POSIX :: Linux
Classifier: Programming Language :: Python
Classifier: Programming Language :: Python :: 3.6
Classifier: Programming Language :: Python :: 3.8
Classifier: Topic :: Software Development :: Quality Assurance
Classifier: Topic :: Scientific/Engineering
Requires-Dist: setuptools
Requires-Dist: numpy>=1.12.0
Requires-Dist: scipy>=0.19.0
Requires-Dist: six>=1.10.0
Requires-Dist: future>=0.16.0
Requires-Dist: gitdb
Requires-Dist: gitpython
Requires-Dist: pyyaml>=3.12
Requires-Dist: stevedore>=1.21
Requires-Dist: pylint>=1.7.1
Requires-Dist: odfpy==1.3.4
Requires-Dist: jinja2>=2.10
Requires-Dist: openpyxl>=2.5.6
Requires-Dist: pytest ; extra == "test"
Requires-Dist: pytest-cov ; extra == "test"
Requires-Dist: tox ; extra == "test"
Requires-Dist: flake8 ; extra == "test"
Requires-Dist: xmldiff==2.4 ; extra == "test"
Provides-Extra: test
